CHANGELOG
LICENSE.txt
MANIFEST.in
setup.py
misc/python-workers.spec
tests/__init__.py
tests/__init__.pyc
tests/test_workerpool.py
tests/test_workerpool.pyc
tests/x.py
workers/__init__.py
workers/processpool.py
workers/workerpool.py
workers.egg-info/PKG-INFO
workers.egg-info/SOURCES.txt
workers.egg-info/dependency_links.txt
workers.egg-info/top_level.txt