Metadata-Version: 1.0
Name: workers
Version: 0.1
Summary: Workers, a work pool library for threads!
Home-page: http://opensource.nasuni.com/workers
Author: Jesse Noller
Author-email: jnoller@gmail.com
License: Apache Software License 2.0
Keywords: threads threadpool parallel
Platform: UNKNOWN
